restsession/__init__.py
restsession/default_hooks.py
restsession/defaults.py
restsession/exceptions.py
restsession/metaclass.py
restsession/models.py
restsession/session.py
restsession/session_singleton.py
restsession-1.0.3.dist-info/LICENSE
restsession-1.0.3.dist-info/METADATA
restsession-1.0.3.dist-info/WHEEL
restsession-1.0.3.dist-info/RECORD
