Metadata-Version: 2.3
Name: restsession
Version: 1.0.3
Summary: RESTful API-friendly implementation of the 'requests' library
License: MIT
Author: Palmer Sample
Author-email: palmer@palmersample.net
Requires-Python: >=3.10,<4.0
Classifier: Development Status :: 5 - Production/Stable
Classifier: Intended Audience :: Developers
Classifier: License :: OSI Approved :: MIT License
Classifier: Operating System :: OS Independent
Classifier: Programming Language :: Python
Classifier: Programming Language :: Python :: 3
Classifier: Programming Language :: Python :: 3.9
Classifier: Programming Language :: Python :: 3.10
Classifier: Programming Language :: Python :: 3.11
Classifier: Programming Language :: Python :: 3.12
Classifier: Programming Language :: Python :: 3.13
Classifier: Programming Language :: Python :: 3 :: Only
Requires-Dist: pydantic (>=2.12.5,<2.13.0)
Requires-Dist: requests (>=2.32.5,<2.33.0)
Requires-Dist: urllib3 (>=2.6.3,<2.7.0)
Project-URL: Bug Tracker, https://github.com/palmersample/restsession/issues
Project-URL: Homepage, https://github.com/palmersample/restsession
